[
    {
        "name": "Nồi chiên không dầu Rapido SMART-7.0M 7 lít",
        "size": "",
        "resolution": "",
        "price_old": "2490000",
        "discount": "-52%",
        "price_sale": "1190000",
        "rating": "4",
        "rating_number": "135",
        "product_img": "https://cdn.tgdd.vn/Products/Images/9418/307646/noi-chien-khong-dau-rapido-smart-70m-7-lit-240523-094953-600x600.jpg"
    },
    {
        "name": "Nồi chiên không dầu AVA 55K07A 5.5 lít",
        "size": "",
        "resolution": "",
        "price_old": "2590000",
        "discount": "-61%",
        "price_sale": "990000",
        "rating": "4",
        "rating_number": "848",
        "product_img": "https://cdn.tgdd.vn/Products/Images/9418/240291/Ava-55K07A-0-600x600.jpg"
    },
    {
        "name": "Nồi chiên không dầu Philips HD9200/90 2.4 lít",
        "size": "",
        "resolution": "",
        "price_old": "2850000",
        "discount": "-37%",
        "price_sale": "1790000",
        "rating": "5",
        "rating_number": "292",
        "product_img": "https://cdn.tgdd.vn/Products/Images/9418/231967/Philips-HD9200-90-0-600x600.jpg"
    },
    {
        "name": "Nồi chiên không dầu Bear QZG-A15T2 4.5 lít",
        "size": "",
        "resolution": "",
        "price_old": "3565000",
        "discount": "-70%",
        "price_sale": "1050000",
        "rating": "4",
        "rating_number": "25",
        "product_img": "https://cdn.tgdd.vn/Products/Images/9418/292764/noi-chien-khong-dau-bear-qzg-a15t2-45-lit-290723-013104-600x600.jpg"
    },
    {
        "name": "Lò chiên không dầu Kangaroo KG12AF1A 12 lít",
        "size": "",
        "resolution": "",
        "price_old": "6040000",
        "discount": "-57%",
        "price_sale": "2590000",
        "rating": "4",
        "rating_number": "511",
        "product_img": "https://cdn.tgdd.vn/Products/Images/9418/242418/lo-chien-khong-dau-kangaroo-kg12af1a-12-lit-170423-120402-600x600.jpg"
    },
    {
        "name": "Nồi chiên không dầu Rapido RAF5.0M 5 lít",
        "size": "",
        "resolution": "",
        "price_old": "",
        "discount": "",
        "price_sale": "1700000",
        "rating": "4",
        "rating_number": "169",
        "product_img": "https://cdn.tgdd.vn/Products/Images/9418/228885/rapido-raf50m-0-600x600-3.jpg"
    },
    {
        "name": "Nồi chiên không dầu AVA AF40155D 5 lít",
        "size": "",
        "resolution": "",
        "price_old": "2290000",
        "discount": "-58%",
        "price_sale": "950000",
        "rating": "4",
        "rating_number": "582",
        "product_img": "https://cdn.tgdd.vn/Products/Images/9418/235357/AVA-AF40155D-0-600x600.jpg"
    },
    {
        "name": "Nồi chiên không dầu Sharp KF-AF70EV-BK 7 lít",
        "size": "",
        "resolution": "",
        "price_old": "3090000",
        "discount": "-8%",
        "price_sale": "2815000",
        "rating": "4",
        "rating_number": "181",
        "product_img": "https://cdn.tgdd.vn/Products/Images/9418/258343/Sharp-KF-AF70EV-BK-0-min-600x600.jpg"
    },
    {
        "name": "Nồi chiên không dầu Kangaroo KG55AF1A 5.2 lít",
        "size": "",
        "resolution": "",
        "price_old": "4270000",
        "discount": "-60%",
        "price_sale": "1690000",
        "rating": "4",
        "rating_number": "174",
        "product_img": "https://cdn.tgdd.vn/Products/Images/9418/217595/Kangaroo-KG55AF1A-0-600x600.jpg"
    },
    {
        "name": "Nồi chiên không dầu Sunhouse SHD4035 9 lít",
        "size": "",
        "resolution": "",
        "price_old": "3450000",
        "discount": "-40%",
        "price_sale": "2070000",
        "rating": "4",
        "rating_number": "319",
        "product_img": "https://cdn.tgdd.vn/Products/Images/9418/275125/275125-600x600-1.jpg"
    },
    {
        "name": "Nồi chiên không dầu Kangaroo KG42AF1 4 lít",
        "size": "",
        "resolution": "",
        "price_old": "3360000",
        "discount": "-70%",
        "price_sale": "990000",
        "rating": "4",
        "rating_number": "69",
        "product_img": "https://cdn.tgdd.vn/Products/Images/9418/217555/Kangaroo-KG42AF1-0-600x600.jpg"
    },
    {
        "name": "Nồi chiên không dầu AVA KDF-593D 7.5 lít",
        "size": "",
        "resolution": "",
        "price_old": "2890000",
        "discount": "-55%",
        "price_sale": "1290000",
        "rating": "4",
        "rating_number": "700",
        "product_img": "https://cdn.tgdd.vn/Products/Images/9418/240313/ava-kdf-593d-0-600x600-1.jpg"
    },
    {
        "name": "Nồi chiên không dầu Rapido RAF-8.0M 8 lít",
        "size": "",
        "resolution": "",
        "price_old": "2990000",
        "discount": "-56%",
        "price_sale": "1290000",
        "rating": "4",
        "rating_number": "35",
        "product_img": "https://cdn.tgdd.vn/Products/Images/9418/304773/noi-chien-khong-dau-rapido-raf-80m-8-lit-310323-110541-600x600.jpg"
    },
    {
        "name": "Nồi chiên không dầu Sunhouse SHD4062 6 lít",
        "size": "",
        "resolution": "",
        "price_old": "2790000",
        "discount": "-44%",
        "price_sale": "1550000",
        "rating": "4",
        "rating_number": "321",
        "product_img": "https://cdn.tgdd.vn/Products/Images/9418/258338/Sunhouse-SHD4062-0-min-600x600.jpg"
    },
    {
        "name": "Nồi chiên không dầu Hafele AF-T5A (535.43.712) 5 lít",
        "size": "",
        "resolution": "",
        "price_old": "3990000",
        "discount": "-40%",
        "price_sale": "2390000",
        "rating": "4",
        "rating_number": "114",
        "product_img": "https://cdn.tgdd.vn/Products/Images/9418/233494/Hafele-AF-T5A-0-600x600.jpg"
    }
]